swarmauri_tool_jupyterexecutenotebook/JupyterExecuteNotebookTool.py
swarmauri_tool_jupyterexecutenotebook/__init__.py
swarmauri_tool_jupyterexecutenotebook-0.7.5.dist-info/LICENSE
swarmauri_tool_jupyterexecutenotebook-0.7.5.dist-info/METADATA
swarmauri_tool_jupyterexecutenotebook-0.7.5.dist-info/WHEEL
swarmauri_tool_jupyterexecutenotebook-0.7.5.dist-info/entry_points.txt
swarmauri_tool_jupyterexecutenotebook-0.7.5.dist-info/RECORD
