Metadata-Version: 2.3
Name: swarmauri_tool_jupyterexecutenotebook
Version: 0.7.5
Summary: A tool designed to execute all cells in a Jupyter Notebook using nbconvert’s ExecutePreprocessor, capturing outputs for testing and reporting.
License: Apache-2.0
Author: Jacob Stewart
Author-email: jacob@swarmauri.com
Requires-Python: >=3.10,<3.13
Classifier: License :: OSI Approved :: Apache Software License
Classifier: Programming Language :: Python :: 3.10
Classifier: Programming Language :: Python :: 3.11
Classifier: Programming Language :: Python :: 3.12
Classifier: Programming Language :: Python :: 3.13
Requires-Dist: ipykernel (>=6.29.5)
Requires-Dist: nbconvert (>=7.16.6)
Requires-Dist: nbformat (>=5.10.4)
Requires-Dist: swarmauri_base
Requires-Dist: swarmauri_core
Requires-Dist: swarmauri_standard
